nonebot_plugin_get_nickname/__init__.py
nonebot_plugin_get_nickname/errors.py
nonebot_plugin_get_nickname/func_manager.py
nonebot_plugin_get_nickname/get_bot_nickname/__init__.py
nonebot_plugin_get_nickname/get_bot_nickname/onebot_v11.py
nonebot_plugin_get_nickname/get_bot_nickname/qqguild.py
nonebot_plugin_get_nickname/get_nickname/__init__.py
nonebot_plugin_get_nickname/get_nickname/onebot_v11.py
nonebot_plugin_get_nickname/get_nickname/qqguild.py
nonebot_plugin_get_nickname-0.1.1.post1.dist-info/LICENSE
nonebot_plugin_get_nickname-0.1.1.post1.dist-info/METADATA
nonebot_plugin_get_nickname-0.1.1.post1.dist-info/WHEEL
nonebot_plugin_get_nickname-0.1.1.post1.dist-info/RECORD
