Metadata-Version: 2.1
Name: nonebot-plugin-get-nickname
Version: 0.1.1.post1
Summary: 
Author: ssttkkl
Author-email: huang.wen.long@hotmail.com
Requires-Python: >=3.9,<4.0
Classifier: Programming Language :: Python :: 3
Classifier: Programming Language :: Python :: 3.9
Classifier: Programming Language :: Python :: 3.10
Classifier: Programming Language :: Python :: 3.11
Requires-Dist: nonebot-plugin-session (>=0.0.3)
Requires-Dist: nonebot2 (>=2.0.0,<3.0.0)
